gdalwrap/__init__.py
gdalwrap/core.py
gdalwrap/tools.py
gdalwrap-1.1.1.dist-info/METADATA
gdalwrap-1.1.1.dist-info/WHEEL
gdalwrap-1.1.1.dist-info/licenses/LICENSE
gdalwrap-1.1.1.dist-info/RECORD
