Metadata-Version: 2.1
Name: gdalwrap
Version: 1.1.1
Summary: GDAL python bindings wrapper and helper functions.
Project-URL: Homepage, https://github.com/Rodrigo-NH/gdalwrap
Project-URL: Bug Tracker, https://github.com/Rodrigo-NH/gdalwrap/issues
Author-email: Rodrigo Nascimento Hernandez <rodrigomdev@gmail.com>
License-File: LICENSE
Classifier: Development Status :: 4 - Beta
Classifier: Framework :: IPython
Classifier: Intended Audience :: Developers
Classifier: License :: OSI Approved :: BSD License
Classifier: Operating System :: OS Independent
Classifier: Programming Language :: Python
Classifier: Topic :: Scientific/Engineering :: GIS
Requires-Python: >=3.1
